Topsis_Paryagdeep_101903573/__init__.py
Topsis_Paryagdeep_101903573/topsis_Paryagdeep.py
Topsis_Paryagdeep_101903573-0.0.3.dist-info/METADATA
Topsis_Paryagdeep_101903573-0.0.3.dist-info/WHEEL
Topsis_Paryagdeep_101903573-0.0.3.dist-info/entry_points.txt
Topsis_Paryagdeep_101903573-0.0.3.dist-info/top_level.txt
Topsis_Paryagdeep_101903573-0.0.3.dist-info/RECORD
