Metadata-Version: 2.1
Name: Topsis-Paryagdeep-101903573
Version: 0.0.3
Summary: TOPSIS is a method of compensatory aggregation that compares a set of alternatives by identifying weights for each criterion, normalising scores for each criterion and calculating the geometric distance between each alternative and the ideal alternative, which is the best score in each criterion.
Home-page: https://github.com/Paryaxify/Topsis-Paryagdeep-101903573.git
Author: Paryagdeep Singh
Author-email: psingh4_be19@thapar.edu
License: UNKNOWN
Keywords: TOPSIS,PANDAS,AGGREGATION
Platform: UNKNOWN
Classifier: Programming Language :: Python :: 3
Classifier: License :: OSI Approved :: MIT License
Classifier: Operating System :: OS Independent
Requires-Python: >=3.10
Requires-Dist: pandas
Requires-Dist: openpyxl
